axonius_api_client/__init__.py
axonius_api_client/connect.py
axonius_api_client/data.py
axonius_api_client/exceptions.py
axonius_api_client/features.py
axonius_api_client/http.py
axonius_api_client/logs.py
axonius_api_client/setup_env.py
axonius_api_client/tools.py
axonius_api_client/version.py
axonius_api_client/api/__init__.py
axonius_api_client/api/api_endpoint.py
axonius_api_client/api/api_endpoints.py
axonius_api_client/api/mixins.py
axonius_api_client/api/adapters/__init__.py
axonius_api_client/api/adapters/adapters.py
axonius_api_client/api/adapters/cnx.py
axonius_api_client/api/asset_callbacks/__init__.py
axonius_api_client/api/asset_callbacks/base.py
axonius_api_client/api/asset_callbacks/base_csv.py
axonius_api_client/api/asset_callbacks/base_json.py
axonius_api_client/api/asset_callbacks/base_json_to_csv.py
axonius_api_client/api/asset_callbacks/base_table.py
axonius_api_client/api/asset_callbacks/base_xlsx.py
axonius_api_client/api/asset_callbacks/base_xml.py
axonius_api_client/api/asset_callbacks/tools.py
axonius_api_client/api/assets/__init__.py
axonius_api_client/api/assets/asset_mixin.py
axonius_api_client/api/assets/devices.py
axonius_api_client/api/assets/fields.py
axonius_api_client/api/assets/labels.py
axonius_api_client/api/assets/runner.py
axonius_api_client/api/assets/saved_query.py
axonius_api_client/api/assets/users.py
axonius_api_client/api/assets/vulnerabilities.py
axonius_api_client/api/enforcements/__init__.py
axonius_api_client/api/enforcements/enforcements.py
axonius_api_client/api/enforcements/tasks.py
axonius_api_client/api/folders/__init__.py
axonius_api_client/api/folders/folders.py
axonius_api_client/api/json_api/__init__.py
axonius_api_client/api/json_api/base.py
axonius_api_client/api/json_api/base2.py
axonius_api_client/api/json_api/central_core.py
axonius_api_client/api/json_api/count_operator.py
axonius_api_client/api/json_api/custom_fields.py
axonius_api_client/api/json_api/dashboard_spaces.py
axonius_api_client-5.0.22.dist-info/LICENSE
axonius_api_client-5.0.22.dist-info/METADATA
axonius_api_client-5.0.22.dist-info/WHEEL
axonius_api_client-5.0.22.dist-info/entry_points.txt
axonius_api_client-5.0.22.dist-info/top_level.txt
axonius_api_client-5.0.22.dist-info/RECORD
